itk_subdivisionquadedgemeshfilter-2.0.2.dist-info/RECORD
itk_subdivisionquadedgemeshfilter-2.0.2.dist-info/WHEEL
itk_subdivisionquadedgemeshfilter-2.0.2.dist-info/METADATA
itk_subdivisionquadedgemeshfilter-2.0.2.dist-info/licenses/LICENSE
itk_subdivisionquadedgemeshfilter.libs/libtbb-f489fd38.so.12.9
itk/itkTriangleEdgeCellSubdivisionQuadEdgeMeshFilterPython.py
itk/itkEdgeLengthTriangleEdgeCellSubdivisionCriterionPython.py
itk/itkLoopTriangleEdgeCellSubdivisionQuadEdgeMeshFilterPython.py
itk/_SubdivisionQuadEdgeMeshFilterPython.abi3.so
itk/itkModifiedButterflyTriangleCellSubdivisionQuadEdgeMeshFilterPython.py
itk/itkModifiedButterflyTriangleEdgeCellSubdivisionQuadEdgeMeshFilterPython.py
itk/itkSquareThreeTriangleCellSubdivisionQuadEdgeMeshFilterPython.py
itk/itkLoopTriangleCellSubdivisionQuadEdgeMeshFilterPython.py
itk/itkLinearTriangleCellSubdivisionQuadEdgeMeshFilterPython.py
itk/itkIterativeTriangleCellSubdivisionQuadEdgeMeshFilterPython.py
itk/itkLinearTriangleEdgeCellSubdivisionQuadEdgeMeshFilterPython.py
itk/itkConditionalSubdivisionQuadEdgeMeshFilterPython.py
itk/itkQuadEdgeMeshSubdivisionCriterionPython.py
itk/itkTriangleCellSubdivisionQuadEdgeMeshFilterPython.py
itk/itkCellAreaTriangleCellSubdivisionCriterionPython.py
itk/SubdivisionQuadEdgeMeshFilterPython.py
itk/itkSubdivisionQuadEdgeMeshFilterPython.py
itk/Configuration/SubdivisionQuadEdgeMeshFilterConfig.py
itk/Configuration/SubdivisionQuadEdgeMeshFilter_snake_case.py
