Metadata-Version: 2.1
Name: itk-subdivisionquadedgemeshfilter
Version: 2.0.2
Summary: ITK classes for triangle mesh subdivision
Keywords: itk,InsightToolkit,Geometry,Mesh
Author-Email: Wanlin Zhu <wanlin.zhu@unsw.edu.au>
License: Apache License
Classifier: Development Status :: 4 - Beta
Classifier: Intended Audience :: Developers
Classifier: Intended Audience :: Education
Classifier: Intended Audience :: Healthcare Industry
Classifier: Intended Audience :: Science/Research
Classifier: License :: OSI Approved :: Apache Software License
Classifier: Operating System :: Android
Classifier: Operating System :: MacOS
Classifier: Operating System :: Microsoft :: Windows
Classifier: Operating System :: POSIX
Classifier: Operating System :: Unix
Classifier: Programming Language :: C++
Classifier: Programming Language :: Python
Classifier: Topic :: Scientific/Engineering
Classifier: Topic :: Scientific/Engineering :: Information Analysis
Classifier: Topic :: Scientific/Engineering :: Medical Science Apps.
Classifier: Topic :: Software Development :: Libraries
Project-URL: Download, https://github.com/InsightSoftwareConsortium/ITKSubdivisionQuadEdgeMeshFilter
Project-URL: Homepage, https://github.com/InsightSoftwareConsortium/ITKSubdivisionQuadEdgeMeshFilter
Requires-Python: >=3.9
Requires-Dist: itk==5.4.*
